kclii/consts/envs.py
kclii/database/__init__.py
kclii/database/database.py
kclii/envs/envs.py
kclii/error/database.py
kclii/helper/__init__.py
kclii/helper/data.py
kclii/helper/message.py
kclii/init.py
kclii/main.py
kclii/modules/__init__.py
kclii/modules/profiles/__init__.py
kclii/modules/profiles/core.py
kclii/modules/profiles/models.py
kclii/modules/profiles/profiles.py
kclii/modules/profiles/repository.py
kclii/scripts/__init__.py
kclii/scripts/koff.py
kclii/scripts/kon.py
kclii/scripts/scripts.py
kclii-0.1.13.dist-info/entry_points.txt
kclii-0.1.13.dist-info/WHEEL
kclii-0.1.13.dist-info/METADATA
kclii-0.1.13.dist-info/RECORD
